MANIFEST.in
README.rst
setup.py
such_amaze_lib/__init__.py
such_amaze_lib/decorators.py
such_amaze_lib/file_management.py
such_amaze_lib/gmail_sender.py
such_amaze_lib/keystroke.py
such_amaze_lib/serial_tools.py
such_amaze_lib/xml_tools.py
such_amaze_lib.egg-info/PKG-INFO
such_amaze_lib.egg-info/SOURCES.txt
such_amaze_lib.egg-info/dependency_links.txt
such_amaze_lib.egg-info/top_level.txt
such_amaze_lib/windows_interaction/__init__.py
such_amaze_lib/windows_interaction/mouse.py
such_amaze_lib/windows_interaction/screen.py