Metadata-Version: 1.1
Name: such-amaze-lib
Version: 0.5.1
Summary: Such Amaze Library, Much Wow Functions
Home-page: https://bitbucket.org/BlaiseFulpin/such_amaze_lib
Author: Blaise Fulpin
Author-email: blaise.fulpin@gmail.com
License: UNKNOWN
Platform: UNKNOWN
Classifier: Programming Language :: Python
Classifier: Natural Language :: French
Classifier: Operating System :: OS Independent
Classifier: Programming Language :: Python :: 2.7
